odoo/addons/shopinvader_easy_binding/README.rst
odoo/addons/shopinvader_easy_binding/__init__.py
odoo/addons/shopinvader_easy_binding/__manifest__.py
odoo/addons/shopinvader_easy_binding/hooks.py
odoo/addons/shopinvader_easy_binding/demo/res_company.xml
odoo/addons/shopinvader_easy_binding/i18n/shopinvader_easy_binding.pot
odoo/addons/shopinvader_easy_binding/models/__init__.py
odoo/addons/shopinvader_easy_binding/models/product_product.py
odoo/addons/shopinvader_easy_binding/models/product_template.py
odoo/addons/shopinvader_easy_binding/models/res_company.py
odoo/addons/shopinvader_easy_binding/models/res_config_settings.py
odoo/addons/shopinvader_easy_binding/models/shopinvader_company_backend_mixin.py
odoo/addons/shopinvader_easy_binding/readme/CONFIGURE.rst
odoo/addons/shopinvader_easy_binding/readme/CONTRIBUTORS.rst
odoo/addons/shopinvader_easy_binding/readme/DESCRIPTION.rst
odoo/addons/shopinvader_easy_binding/readme/ROADMAP.rst
odoo/addons/shopinvader_easy_binding/readme/USAGE.rst
odoo/addons/shopinvader_easy_binding/static/description/index.html
odoo/addons/shopinvader_easy_binding/static/description/product_form.png
odoo/addons/shopinvader_easy_binding/tests/__init__.py
odoo/addons/shopinvader_easy_binding/tests/test_shopinvader_company_backend.py
odoo/addons/shopinvader_easy_binding/views/product_template.xml
odoo/addons/shopinvader_easy_binding/views/res_config_settings.xml
odoo14_addon_shopinvader_easy_binding-14.0.1.0.1.dist-info/METADATA
odoo14_addon_shopinvader_easy_binding-14.0.1.0.1.dist-info/WHEEL
odoo14_addon_shopinvader_easy_binding-14.0.1.0.1.dist-info/top_level.txt
odoo14_addon_shopinvader_easy_binding-14.0.1.0.1.dist-info/RECORD
